{
  "publicPath": "/_nuxt/",
  "all": [
    "../server/index.spa.html",
    "152a2e0.js",
    "318d1db.js",
    "3a0ec1f.js",
    "65fbbf0.js",
    "72cd0d1.js",
    "8fda0a5.js",
    "LICENSES",
    "dcf7e7f.js",
    "e8edaa2.js",
    "f182957.js"
  ],
  "initial": [
    "e8edaa2.js",
    "3a0ec1f.js",
    "dcf7e7f.js",
    "72cd0d1.js"
  ],
  "async": [
    "152a2e0.js",
    "318d1db.js",
    "65fbbf0.js",
    "8fda0a5.js",
    "f182957.js"
  ],
  "modules": {
    "15902337": [
      3
    ],
    "27893608": [
      3
    ],
    "32617113": [
      3
    ],
    "33740239": [
      3
    ],
    "40237398": [
      8
    ],
    "40626882": [
      8
    ],
    "51935767": [
      3
    ],
    "55270878": [
      8
    ],
    "62695621": [
      3
    ],
    "63926347": [
      8
    ],
    "66711582": [
      8
    ],
    "79011670": [
      5
    ],
    "79999182": [
      8
    ],
    "62b65270": [
      3
    ],
    "f6cc5efc": [
      3
    ],
    "a4f0bf2e": [
      3
    ],
    "507e7835": [
      3
    ],
    "2d8732de": [
      3
    ],
    "00eafdb5": [
      3
    ],
    "180e9abc": [
      3
    ],
    "2c398f02": [
      3
    ],
    "0a76b5e4": [
      3
    ],
    "a0c8b4d2": [
      3
    ],
    "4a9dccac": [
      5
    ],
    "145ac47c": [
      3
    ],
    "0c846033": [
      3
    ],
    "6ae66cf5": [
      3
    ],
    "40a5c452": [
      3
    ],
    "a6d80166": [
      3
    ],
    "66affa71": [
      3
    ],
    "2f8be812": [
      3
    ],
    "26bc70fb": [
      3
    ],
    "04f67834": [
      3
    ],
    "0e6c5b3f": [
      3
    ],
    "ed09c4a8": [
      3
    ],
    "df9ecf70": [
      3
    ],
    "079f0917": [
      3
    ],
    "b9f76da4": [
      3
    ],
    "93957df6": [
      3
    ],
    "64c34019": [
      3
    ],
    "04c5cb04": [
      3
    ],
    "dbf22ada": [
      3
    ],
    "7e7456ea": [
      3
    ],
    "7521103c": [
      3
    ],
    "5632d574": [
      3
    ],
    "0004d178": [
      3
    ],
    "976fd1fc": [
      3
    ],
    "25a5f69e": [
      3
    ],
    "5930b2e4": [
      3
    ],
    "4ec74423": [
      3
    ],
    "773af812": [
      3
    ],
    "6a39e2a4": [
      3
    ],
    "706ca8ce": [
      3
    ],
    "20d992f8": [
      3
    ],
    "9176ddd4": [
      3
    ],
    "1818b720": [
      3
    ],
    "4d77bd91": [
      3
    ],
    "41ef300e": [
      3
    ],
    "b76f358c": [
      3
    ],
    "514b651c": [
      3
    ],
    "64802c8d": [
      3
    ],
    "358d2def": [
      3
    ],
    "0438acdd": [
      3
    ],
    "16de8028": [
      3
    ],
    "6dbada9d": [
      3
    ],
    "79e935ec": [
      3
    ],
    "016601cd": [
      3
    ],
    "78f3a321": [
      3
    ],
    "53bf4990": [
      3
    ],
    "9455fc2e": [
      5
    ],
    "3f09388a": [
      5
    ],
    "0277aca0": [
      5
    ],
    "c4e58630": [
      5
    ],
    "bdfb01c2": [
      5
    ],
    "84aed14c": [
      5
    ],
    "3a5c122f": [
      5
    ],
    "792414f4": [
      5
    ],
    "34a047f7": [
      5
    ],
    "f39dde60": [
      5
    ],
    "72ca14cc": [
      5
    ],
    "34eebfc8": [
      5
    ],
    "4264c9e8": [
      5
    ],
    "3a6f4b8c": [
      5
    ],
    "e6962188": [
      5
    ],
    "7c515086": [
      5
    ],
    "6ad05458": [
      5
    ],
    "0ddc9376": [
      5
    ],
    "2b989f09": [
      5
    ],
    "a470549e": [
      5
    ],
    "06b87352": [
      3
    ],
    "2c992520": [
      3
    ],
    "e870a84e": [
      3
    ],
    "a2977b44": [
      3
    ],
    "a95a9174": [
      3
    ],
    "cb57f0a8": [
      3
    ],
    "dcd403a2": [
      3
    ],
    "52c94543": [
      3
    ],
    "691fcf54": [
      3
    ],
    "3ca6f406": [
      3
    ],
    "4efa9d2c": [
      3
    ],
    "75b79491": [
      3
    ],
    "2598af6b": [
      3
    ],
    "0a07840f": [
      3
    ],
    "b785bf7e": [
      3
    ],
    "1a13c177": [
      3
    ],
    "7e50dee4": [
      3
    ],
    "10355ae0": [
      3
    ],
    "10defb7e": [
      3
    ],
    "00b3292e": [
      3
    ],
    "67a1d62e": [
      3
    ],
    "5f0c7361": [
      8
    ],
    "50d35a71": [
      8
    ],
    "6be3ece2": [
      3
    ],
    "12ad4df0": [
      3
    ],
    "c7bb6bb2": [
      3
    ],
    "1d7fcc39": [
      3
    ],
    "672dd1d8": [
      3
    ],
    "5fe6c918": [
      3
    ],
    "07ad1fa9": [
      3
    ],
    "32f885a2": [
      3
    ],
    "0e3eee85": [
      3
    ],
    "3046db22": [
      3
    ],
    "361a047e": [
      3
    ],
    "424b04d4": [
      3
    ],
    "ecdfc9c4": [
      3
    ],
    "3cb33f42": [
      3
    ],
    "7658a1fa": [
      3
    ],
    "991c39e8": [
      3
    ],
    "a8ba619c": [
      3
    ],
    "1cf72096": [
      8
    ],
    "75525dea": [
      8
    ],
    "7e0e7f66": [
      8
    ],
    "acfe1e10": [
      8
    ],
    "7dc23574": [
      3
    ],
    "48a7a2ec": [
      3
    ],
    "77e40324": [
      3
    ],
    "1288b7e8": [
      3
    ],
    "61f3cdd6": [
      3
    ],
    "d5db843c": [
      3
    ],
    "1f43864a": [
      3
    ],
    "8072ac1a": [
      3
    ],
    "1f44e7e0": [
      3
    ],
    "6a19b32b": [
      3
    ],
    "0e420cb1": [
      3
    ],
    "1582e530": [
      3
    ],
    "3ac05e3e": [
      3
    ],
    "9b519894": [
      3
    ],
    "93ffdf60": [
      3
    ],
    "03268e92": [
      3
    ],
    "bfcb0be6": [
      3
    ],
    "102b546c": [
      3
    ],
    "d078778a": [
      3
    ],
    "507ac6bc": [
      3
    ],
    "2b5fa035": [
      3
    ],
    "0c24937e": [
      3
    ],
    "9ac85412": [
      3
    ],
    "d175bb36": [
      3
    ],
    "267af7ed": [
      5
    ],
    "605eca8e": [
      3
    ],
    "cb479764": [
      3
    ],
    "09ca0a39": [
      3
    ],
    "b8396424": [
      3
    ],
    "2beadcf8": [
      3
    ],
    "79264ed5": [
      3
    ],
    "19e03542": [
      3
    ],
    "4451bd0b": [
      3
    ],
    "7b3c38f4": [
      3
    ],
    "f05e3fb4": [
      3
    ],
    "0485b59a": [
      3
    ],
    "4eae3040": [
      3
    ],
    "7ca57cec": [
      3
    ],
    "b766b804": [
      3
    ],
    "422385ed": [
      3
    ],
    "6ba2e813": [
      3
    ],
    "5f5b0058": [
      3
    ],
    "0d197efb": [
      3
    ],
    "49ea554d": [
      3
    ],
    "484520c4": [
      3
    ],
    "55b188fc": [
      3
    ],
    "5b3ad546": [
      3
    ],
    "f4ce595a": [
      3
    ],
    "24fb195e": [
      3
    ],
    "0aa5f508": [
      3
    ],
    "0a8d68fe": [
      3
    ],
    "2dd2d3aa": [
      3
    ],
    "c866f6f0": [
      3
    ],
    "7f7a4502": [
      3
    ],
    "7ea187a1": [
      5
    ],
    "1c6d7183": [
      8
    ],
    "0a3008ad": [
      3
    ],
    "2bf9f2b4": [
      3
    ],
    "26c1cf9c": [
      3
    ],
    "703ca2c3": [
      3
    ],
    "738c1c90": [
      3
    ],
    "3e504aee": [
      3
    ],
    "613beeac": [
      3
    ],
    "616c3aff": [
      3
    ],
    "3acede48": [
      3
    ],
    "5167e5ee": [
      3
    ],
    "5dea8f04": [
      3
    ],
    "4a08a54f": [
      3
    ],
    "0022b0dc": [
      3
    ],
    "1407422e": [
      3
    ],
    "58993b98": [
      3
    ],
    "7f4f5572": [
      3
    ],
    "6f074cbb": [
      3
    ],
    "16789c60": [
      3
    ],
    "25a5beae": [
      3
    ],
    "57d90795": [
      3
    ],
    "e081cfb6": [
      3
    ],
    "27775d16": [
      3
    ],
    "17f86332": [
      3
    ],
    "5ad57cc2": [
      3
    ],
    "5476b292": [
      3
    ],
    "2710dc0d": [
      3
    ],
    "6b4d3aa0": [
      3
    ],
    "150b1251": [
      3
    ],
    "475aa275": [
      3
    ],
    "d62fd7f4": [
      3
    ],
    "3365efb1": [
      3
    ],
    "eb7ef17c": [
      3
    ],
    "b7340f1e": [
      3
    ],
    "24a46a46": [
      3
    ],
    "5de427ea": [
      3
    ],
    "06b1c160": [
      3
    ],
    "e90c06e4": [
      3
    ],
    "2d6904e4": [
      3
    ],
    "36491ad6": [
      3
    ],
    "0d7bd236": [
      3
    ],
    "18dff9ca": [
      5
    ],
    "7eccd0b2": [
      5
    ],
    "0be71772": [
      3
    ],
    "024cbe53": [
      3
    ],
    "17a8ab5a": [
      3
    ],
    "55c4c72e": [
      3
    ],
    "56a0df9e": [
      3
    ],
    "7ad3516a": [
      3
    ],
    "1181c0c1": [
      3
    ],
    "0e5d30a2": [
      8
    ],
    "50e39c3b": [
      3
    ],
    "7da473d2": [
      8
    ],
    "39ddaa0c": [
      8
    ],
    "107bb6ff": [
      3
    ],
    "6dc531c2": [
      5
    ],
    "3c6036d7": [
      8
    ],
    "0469d367": [
      8
    ],
    "3d7eb8c4": [
      8
    ],
    "044205d5": [
      8
    ],
    "aaa4aac2": [
      8
    ],
    "7fbd9162": [
      8
    ],
    "17c72135": [
      8
    ],
    "c0f81538": [
      8
    ],
    "16bfa592": [
      8
    ],
    "20d853cf": [
      8
    ],
    "0764c88f": [
      8
    ],
    "ec520322": [
      8
    ],
    "73344cbd": [
      8
    ],
    "24bf8554": [
      8
    ],
    "085187c7": [
      8
    ],
    "e1d18f90": [
      8
    ],
    "d18ced02": [
      8
    ],
    "b92aeea2": [
      8
    ],
    "3328916a": [
      8
    ],
    "b85ab8ca": [
      8
    ],
    "707fe2e2": [
      8
    ],
    "96060fae": [
      8
    ],
    "43f4dd62": [
      8
    ],
    "16153ca6": [
      8
    ],
    "046712cf": [
      8
    ],
    "578122cf": [
      8
    ],
    "6813ade4": [
      8
    ],
    "5a255051": [
      8
    ],
    "6fae19a0": [
      8
    ],
    "0d0903a5": [
      8
    ],
    "199ea452": [
      8
    ],
    "19c5b8a2": [
      8
    ],
    "3b9549d9": [
      8
    ],
    "0e30fe0f": [
      8
    ],
    "0a61af8a": [
      8
    ],
    "4563ce7e": [
      8
    ],
    "b0821ad8": [
      8
    ],
    "706037c5": [
      8
    ],
    "148fd746": [
      8
    ],
    "819c5886": [
      8
    ],
    "3a32a48f": [
      8
    ],
    "9f0c232a": [
      8
    ],
    "4fb0fa26": [
      8
    ],
    "cfc74c22": [
      8
    ],
    "1651f5a1": [
      8
    ],
    "054b0eb2": [
      8
    ],
    "2a920740": [
      8
    ],
    "1954596f": [
      8
    ],
    "bad79e82": [
      8
    ],
    "7380afa0": [
      8
    ],
    "782bc776": [
      8
    ],
    "762190ba": [
      8
    ],
    "36ca3d8f": [
      8
    ],
    "07df1524": [
      8
    ],
    "60220f36": [
      8
    ],
    "effd3086": [
      8
    ],
    "62fa175c": [
      8
    ],
    "5d810a5b": [
      8
    ],
    "355ec1c2": [
      8
    ],
    "b5361a6c": [
      8
    ],
    "1b22a845": [
      8
    ],
    "658cfb97": [
      8
    ],
    "6c82f648": [
      8
    ],
    "a85cd8f0": [
      8
    ],
    "e5f226ee": [
      8
    ],
    "17a2db96": [
      8
    ],
    "4bf2580f": [
      8
    ],
    "c33917fa": [
      8
    ],
    "697f284f": [
      8
    ],
    "58e0dd67": [
      8
    ],
    "ae60017a": [
      8
    ],
    "d8a00214": [
      8
    ],
    "34c1777a": [
      8
    ],
    "ba74a494": [
      8
    ],
    "a279c296": [
      8
    ],
    "075a628f": [
      8
    ],
    "543352d2": [
      8
    ],
    "465f3b6f": [
      8
    ],
    "8f258ca8": [
      8
    ],
    "0f8dee5d": [
      8
    ],
    "7016a49b": [
      8
    ],
    "5814a4c1": [
      8
    ],
    "74dc5196": [
      8
    ],
    "efba86ee": [
      8
    ],
    "e6c8e152": [
      8
    ],
    "05e4e3c3": [
      8
    ],
    "15ecaeb6": [
      8
    ],
    "48c4ee5a": [
      8
    ],
    "642d55be": [
      8
    ],
    "aa35661c": [
      8
    ],
    "9c3a65ee": [
      8
    ],
    "3820e08e": [
      8
    ],
    "796310c7": [
      8
    ],
    "318882b8": [
      8
    ],
    "d0bb0822": [
      8
    ],
    "469bbcc5": [
      8
    ],
    "5e4019f7": [
      8
    ],
    "5991cd00": [
      8
    ],
    "29f2f33f": [
      8
    ],
    "0783b8c2": [
      8
    ],
    "315374f2": [
      8
    ],
    "32723df4": [
      8
    ],
    "533d0356": [
      8
    ],
    "477573ff": [
      8
    ],
    "2f15c194": [
      8
    ],
    "2627b4b5": [
      8
    ],
    "359bbccf": [
      8
    ],
    "6f3e5fca": [
      8
    ],
    "3a3cc6a3": [
      8
    ],
    "8c6cf3da": [
      8
    ],
    "8684b262": [
      8
    ],
    "7c778142": [
      8
    ],
    "efbf7906": [
      8
    ],
    "4b51358c": [
      8
    ],
    "5e2a8e3a": [
      8
    ],
    "19e924c5": [
      8
    ],
    "564e9d17": [
      8
    ],
    "539c40b3": [
      8
    ],
    "12e04805": [
      8
    ],
    "642a7e60": [
      8
    ],
    "7f6f246e": [
      8
    ],
    "496ae432": [
      8
    ],
    "08a5558d": [
      8
    ],
    "34c6d296": [
      8
    ],
    "6b0b47ee": [
      8
    ],
    "c9319362": [
      8
    ],
    "5e5b54b9": [
      8
    ],
    "8d7d6ad6": [
      8
    ],
    "53debd84": [
      8
    ],
    "33f4487d": [
      8
    ],
    "badbba4a": [
      8
    ],
    "332bf2a6": [
      8
    ],
    "1c7e772a": [
      8
    ],
    "7f1d8de2": [
      8
    ],
    "211fb89a": [
      8
    ],
    "2ba6f962": [
      8
    ],
    "67a2cf1d": [
      8
    ],
    "11fe3087": [
      8
    ],
    "408ddec3": [
      8
    ],
    "24f9ed15": [
      8
    ],
    "3831f488": [
      8
    ],
    "39d279b6": [
      8
    ],
    "8995412e": [
      8
    ],
    "3a9009ef": [
      8
    ],
    "6a3ab8c0": [
      8
    ],
    "f24824d6": [
      8
    ],
    "2327aa42": [
      8
    ],
    "e42ab422": [
      8
    ],
    "0eeb1f2f": [
      8
    ],
    "36c715fd": [
      8
    ],
    "0a04b119": [
      8
    ],
    "747801b9": [
      8
    ],
    "f406a19e": [
      8
    ],
    "f4135c02": [
      8
    ],
    "585d6aa9": [
      8
    ],
    "f40fb90a": [
      8
    ],
    "2c8f145d": [
      8
    ],
    "f702f4aa": [
      8
    ],
    "0dafd3f1": [
      8
    ],
    "6e2fcffc": [
      8
    ],
    "3dfd6384": [
      8
    ],
    "49c3986d": [
      8
    ],
    "2d3ed88e": [
      8
    ],
    "0fd96869": [
      8
    ],
    "55bd66a0": [
      8
    ],
    "417a6e7c": [
      8
    ],
    "7ed7b14f": [
      8
    ],
    "ad807028": [
      8
    ],
    "d03091e2": [
      8
    ],
    "41773ec0": [
      8
    ],
    "b615221c": [
      8
    ],
    "5702e8bf": [
      8
    ],
    "39e1d590": [
      8
    ],
    "a06a5b98": [
      8
    ],
    "132b824e": [
      8
    ],
    "6caf2cea": [
      8
    ],
    "6e4fb218": [
      8
    ],
    "b7c736e8": [
      8
    ],
    "6d274e11": [
      8
    ],
    "3eb32bc0": [
      8
    ],
    "2fce807e": [
      8
    ],
    "5141805e": [
      8
    ],
    "f4b5cd4a": [
      8
    ],
    "0b84d15e": [
      8
    ],
    "7a75d8c8": [
      8
    ],
    "370fc32c": [
      8
    ],
    "f84f371a": [
      8
    ],
    "4cb67970": [
      8
    ],
    "3de68a0b": [
      8
    ],
    "b69dd52e": [
      8
    ],
    "20f936a1": [
      8
    ],
    "9b5fd7a0": [
      8
    ],
    "646a7e23": [
      8
    ],
    "1c6c75a2": [
      8
    ],
    "84ef8968": [
      8
    ],
    "67c7bbb9": [
      8
    ],
    "623e3cd4": [
      8
    ],
    "d8f093e4": [
      8
    ],
    "d673d204": [
      8
    ],
    "2725fd36": [
      8
    ],
    "3d335af6": [
      8
    ],
    "fb0cb226": [
      8
    ],
    "027b4065": [
      8
    ],
    "b52918d2": [
      8
    ],
    "889c8984": [
      8
    ],
    "22daf52e": [
      8
    ],
    "1fd1feae": [
      8
    ],
    "345b7f2e": [
      8
    ],
    "945f9f88": [
      8
    ],
    "10145adf": [
      8
    ],
    "3c79dafe": [
      8
    ],
    "9551fc7a": [
      8
    ],
    "18478f90": [
      8
    ],
    "6e1627f1": [
      8
    ],
    "20f8c9a2": [
      8
    ],
    "335c6f80": [
      8
    ],
    "274cd5e2": [
      8
    ],
    "019e8c03": [
      8
    ],
    "27a0735c": [
      8
    ],
    "23a4d738": [
      8
    ],
    "4ac41417": [
      8
    ],
    "33fae879": [
      8
    ],
    "2ac08366": [
      8
    ],
    "7c7e2cb1": [
      8
    ],
    "16dc655c": [
      8
    ],
    "5c9b9c45": [
      8
    ],
    "2a09a456": [
      8
    ],
    "b242767a": [
      8
    ],
    "2dfe4016": [
      8
    ],
    "1e1cb1dc": [
      8
    ],
    "0387a38a": [
      8
    ],
    "6c123eb7": [
      8
    ],
    "a2918774": [
      8
    ],
    "2f593908": [
      8
    ],
    "b5b90a10": [
      8
    ],
    "1b72c764": [
      8
    ],
    "f1b46ac2": [
      8
    ],
    "206534ed": [
      8
    ],
    "49444c52": [
      8
    ],
    "25c46908": [
      8
    ],
    "712294ee": [
      8
    ],
    "59be1368": [
      8
    ],
    "30702db2": [
      8
    ],
    "bf4e5f4e": [
      8
    ],
    "0518f680": [
      8
    ],
    "98f6beee": [
      8
    ],
    "9e39ae58": [
      8
    ],
    "5fc1db3c": [
      8
    ],
    "3576f290": [
      8
    ],
    "699bd9be": [
      8
    ],
    "4e67fdce": [
      8
    ],
    "076c39c6": [
      8
    ],
    "2ecff8d2": [
      8
    ],
    "47a46e60": [
      8
    ],
    "5b292810": [
      8
    ],
    "5bb2b6a8": [
      8
    ],
    "cd5d5cf6": [
      8
    ],
    "25783b61": [
      8
    ],
    "45cd8280": [
      8
    ],
    "ebb34c22": [
      8
    ],
    "5bbfe8ba": [
      8
    ],
    "01de9eb0": [
      8
    ],
    "fd94a72a": [
      8
    ],
    "04935556": [
      8
    ],
    "a90b6af0": [
      8
    ],
    "3eff0d83": [
      8
    ],
    "6beca817": [
      8
    ],
    "8ba6dcde": [
      8
    ],
    "392e530e": [
      8
    ],
    "fe6da512": [
      8
    ],
    "be0dc21a": [
      8
    ],
    "0e2edf7e": [
      8
    ],
    "424a34f3": [
      8
    ],
    "c11c0018": [
      8
    ],
    "e8b006fa": [
      8
    ],
    "3409c01e": [
      8
    ],
    "38e042f4": [
      8
    ],
    "727e0776": [
      8
    ],
    "e469a34e": [
      8
    ],
    "29b13c79": [
      8
    ],
    "07724372": [
      8
    ],
    "60978a37": [
      8
    ],
    "41595a12": [
      8
    ],
    "6b2beaaf": [
      8
    ],
    "4bff7bad": [
      8
    ],
    "485349cc": [
      8
    ],
    "0fb52be3": [
      8
    ],
    "b4d92280": [
      8
    ],
    "4252ab3c": [
      8
    ],
    "5e3bbb92": [
      8
    ],
    "6cd0e00f": [
      8
    ],
    "080ebdd9": [
      8
    ],
    "4153421a": [
      8
    ],
    "716e0950": [
      3
    ],
    "54f661df": [
      3
    ],
    "0120797b": [
      5
    ],
    "480b9ec4": [
      8
    ],
    "3fe90267": [
      3
    ],
    "70ca29ea": [
      3
    ],
    "3a1b8509": [
      3
    ],
    "784601ca": [
      3
    ],
    "f3d280e0": [
      3
    ],
    "f16d6bbc": [
      3
    ],
    "3704a1f2": [
      3
    ],
    "3889e675": [
      3
    ],
    "b6ef3d46": [
      3
    ],
    "0f372ecd": [
      3
    ],
    "cc60cac4": [
      3
    ],
    "6ee78381": [
      3
    ],
    "3be38998": [
      3
    ],
    "d492ed70": [
      3
    ],
    "1eb2daf4": [
      3
    ],
    "dce13cd2": [
      3
    ],
    "0a74c05a": [
      3
    ],
    "128fbd2a": [
      3
    ],
    "38145da8": [
      3
    ],
    "7da83c9c": [
      3
    ],
    "3c5f404e": [
      3
    ],
    "76f57ff5": [
      3
    ],
    "6f355212": [
      3
    ],
    "4e05d05a": [
      3
    ],
    "16e7bb00": [
      3
    ],
    "52fad7c3": [
      3
    ],
    "035eebf2": [
      3
    ],
    "4660a7fa": [
      3
    ],
    "4af509e4": [
      3
    ],
    "abbec9d0": [
      3
    ],
    "27316af5": [
      5
    ],
    "6cb1ddf4": [
      5
    ],
    "dcff1dfe": [
      5
    ],
    "6d24d6d2": [
      5
    ],
    "41ea580c": [
      8
    ],
    "8bccdf22": [
      8
    ],
    "ecfd6634": [
      8
    ],
    "e57a724a": [
      8
    ],
    "2f0beb35": [
      3
    ],
    "c4f2749c": [
      3
    ],
    "a1cf9630": [
      3
    ],
    "77689e12": [
      3
    ],
    "5e1d5aca": [
      3
    ],
    "e170a1e0": [
      3
    ],
    "516d2f3f": [
      3
    ],
    "abbae0fc": [
      3
    ],
    "43c95891": [
      3
    ],
    "777a51b9": [
      3
    ],
    "06c0fa8f": [
      3
    ],
    "696bef82": [
      3
    ],
    "ebca0ffe": [
      3
    ],
    "2a952c90": [
      3
    ],
    "999e13ce": [
      3
    ],
    "204c9b76": [
      10
    ],
    "60dd2b22": [
      10
    ],
    "41bb08d5": [
      10
    ],
    "086eace6": [
      1
    ],
    "761e2b89": [
      10
    ],
    "0552cfec": [
      10
    ],
    "6bb91f7c": [
      10
    ],
    "3481b17c": [
      10
    ],
    "f03d75a4": [
      10
    ],
    "053db748": [
      10
    ],
    "3c83d6b3": [
      10
    ],
    "7ad6e932": [
      1
    ],
    "42b5d278": [
      1
    ],
    "1b7f5a94": [
      2,
      10
    ],
    "c83a99fc": [
      2,
      10
    ],
    "1f5040be": [
      2,
      10
    ],
    "dc2e2d24": [
      2,
      10
    ],
    "157b85af": [
      2,
      10
    ],
    "22acf336": [
      1
    ],
    "5059804f": [
      1
    ],
    "46aeea8a": [
      1
    ],
    "840a6174": [
      6
    ],
    "295f78ea": [
      6
    ],
    "779f4df7": [
      6
    ]
  },
  "assetsMapping": {
    "51bae372": [
      "152a2e0.js"
    ],
    "2a130dde": [
      "318d1db.js"
    ],
    "085a35c4": [
      "3a0ec1f.js"
    ],
    "3baf99f4": [
      "65fbbf0.js"
    ],
    "1a3ae26b": [
      "72cd0d1.js"
    ],
    "e81092fe": [
      "8fda0a5.js"
    ],
    "7ea24c87": [
      "dcf7e7f.js"
    ],
    "6fca0322": [
      "e8edaa2.js"
    ],
    "692355a2": [
      "f182957.js"
    ]
  }
}